florin/__init__.py
florin/autotuning.py
florin/classification.py
florin/closure.py
florin/compose.py
florin/conncomp.py
florin/context.py
florin/conv_ndnt.py
florin/exposure.py
florin/importwrapper.py
florin/io.py
florin/log_utils.py
florin/morphology.py
florin/ndnt.py
florin/numpy.py
florin/reconstruction.py
florin/run.py
florin/scipy.py
florin/skimage.py
florin/thresholding.py
florin/tiling.py
florin/util.py
florin/graph/__init__.py
florin/graph/florin_graph.py
florin/graph/florin_node.py
florin/pipelines/__init__.py
florin/pipelines/balsam.py
florin/pipelines/mpi.py
florin/pipelines/multiprocess.py
florin/pipelines/multithread.py
florin/pipelines/pipeline.py
florin/pipelines/serial.py
florin/pipelines/workqueue.py
florin-0.0.2.post1.dist-info/LICENSE
florin-0.0.2.post1.dist-info/METADATA
florin-0.0.2.post1.dist-info/WHEEL
florin-0.0.2.post1.dist-info/top_level.txt
florin-0.0.2.post1.dist-info/RECORD
