Metadata-Version: 2.1
Name: florin
Version: 0.0.2.post1
Summary: Fast image segmentation without needing to learn a thing.
Home-page: https://github.com/jeffkinnison/florin
Author: Jeff Kinnison, Elia Shahbazi
Author-email: jkinniso@nd.edu, ashahbaz@nd.edu
License: UNKNOWN
Keywords: machine_learning hyperparameters distributed_computing
Platform: UNKNOWN
Classifier: Development Status :: 3 - Alpha
Classifier: Intended Audience :: Science/Research
Classifier: License :: OSI Approved :: MIT License
Classifier: Programming Language :: Python :: 3
Classifier: Programming Language :: Python :: 3.4
Classifier: Programming Language :: Python :: 3.5
Classifier: Programming Language :: Python :: 3.6
Classifier: Programming Language :: Python :: 3.7
Classifier: Operating System :: POSIX
Classifier: Operating System :: Unix
Classifier: Operating System :: MacOS
Classifier: Topic :: Scientific/Engineering :: Medical Science Apps.
Classifier: Topic :: System :: Distributed Computing
Requires-Dist: cloud-volume
Requires-Dist: h5py
Requires-Dist: mpi4py (>=3.0.0)
Requires-Dist: networkx
Requires-Dist: numpy
Requires-Dist: pathos
Requires-Dist: scikit-image
Requires-Dist: scipy
